_gdb/__init__.pyi
gdbstub-0.2.2.dist-info/licenses/LICENSE
gdbstub-0.2.2.dist-info/METADATA
gdbstub-0.2.2.dist-info/WHEEL
gdbstub-0.2.2.dist-info/top_level.txt
gdbstub-0.2.2.dist-info/RECORD
